setup.cfg
setup.py
webshrinker/__init__.py
webshrinker.egg-info/PKG-INFO
webshrinker.egg-info/SOURCES.txt
webshrinker.egg-info/dependency_links.txt
webshrinker.egg-info/requires.txt
webshrinker.egg-info/top_level.txt