Metadata-Version: 1.1
Name: webshrinker
Version: 2.0
Summary: Provides access to the Web Shrinker API services, including website category lookups.
Home-page: https://github.com/webshrinker/webshrinker-sdk-python
Author: Web Shrinker
Author-email: UNKNOWN
License: LICENSE.txt
Download-URL: https://github.com/webshrinker/webshrinker-sdk-python/tarball/2.0
Platform: UNKNOWN
